handsome/__init__.py
handsome/Boy/__init__.py
handsome/Boy/information.py
handsome/Boy/message.py
ljl_handsome-0.3.dist-info/METADATA
ljl_handsome-0.3.dist-info/WHEEL
ljl_handsome-0.3.dist-info/top_level.txt
ljl_handsome-0.3.dist-info/RECORD
