Metadata-Version: 2.1
Name: ljl-handsome
Version: 0.3
Summary: 队员:梁景洛,肖俊毅
Author: ljl
Author-email: 1712671142@qq.com
License: UNKNOWN
Platform: UNKNOWN
